avanak/__init__.py
avanak/cli.py
avanak/client.py
avanak-0.1.2.dist-info/WHEEL
avanak-0.1.2.dist-info/entry_points.txt
avanak-0.1.2.dist-info/METADATA
avanak-0.1.2.dist-info/RECORD
