Metadata-Version: 2.3
Name: avanak
Version: 0.1.2
Summary: Python client library for Avanak voice message REST API
Keywords: avanak,voice,api,sms,telephony,communication,persian,farsi,ivr,text-to-speech,tts
Author: Hassan Pouralijan
Author-email: Hassan Pouralijan <pouralijan@gmail.com>
License: MIT
Classifier: Development Status :: 4 - Beta
Classifier: Intended Audience :: Developers
Classifier: License :: OSI Approved :: MIT License
Classifier: Operating System :: OS Independent
Classifier: Programming Language :: Python :: 3
Classifier: Programming Language :: Python :: 3.8
Classifier: Programming Language :: Python :: 3.9
Classifier: Programming Language :: Python :: 3.10
Classifier: Programming Language :: Python :: 3.11
Classifier: Programming Language :: Python :: 3.12
Classifier: Programming Language :: Python :: 3.13
Classifier: Programming Language :: Python :: 3.14
Classifier: Topic :: Communications :: Telephony
Classifier: Topic :: Software Development :: Libraries :: Python Modules
Classifier: Topic :: Internet :: WWW/HTTP
Requires-Dist: requests>=2.25.0
Requires-Dist: pydantic>=2.0.0
Requires-Dist: click>=8.0.0
Maintainer: Hassan Pouralijan
Maintainer-email: Hassan Pouralijan <pouralijan@gmail.com>
Requires-Python: >=3.8
